PackBits.pypy310-pp73-x86_64-linux-gnu.so
TonkaConstruction/PackBits.c
TonkaConstruction/Module.py
TonkaConstruction/__init__.py
TonkaConstruction/Engine.py
TonkaConstruction/Background.py
TonkaConstruction/Asset.py
TonkaConstruction-0.9.0.dist-info/METADATA
TonkaConstruction-0.9.0.dist-info/COPYING
TonkaConstruction-0.9.0.dist-info/RECORD
TonkaConstruction-0.9.0.dist-info/top_level.txt
TonkaConstruction-0.9.0.dist-info/entry_points.txt
TonkaConstruction-0.9.0.dist-info/WHEEL
