Metadata-Version: 2.1
Name: TonkaConstruction
Version: 0.9.0
Summary: Extract assets from Tonka Construction (1996)
Author-email: Nathanael Gentry <nathanael.gentrydb8@gmail.com>
License: GNU GENERAL PUBLIC LICENSE
Project-URL: Homepage, https://github.com/npjg/TonkaConstruction
Project-URL: Repository, https://github.com/npjg/TonkaConstruction
Keywords: reverse-engineering
Classifier: Programming Language :: Python :: 3
Classifier: License :: OSI Approved :: GNU General Public License v3 (GPLv3)
Classifier: Operating System :: OS Independent
Requires-Python: >=3.9
License-File: COPYING
Requires-Dist: self-documenting-struct ==0.9.2
Requires-Dist: asset-extraction-framework ==0.9.6
